{
  "FMS": {
    "window": {
      "visible": false
    }
  },
  "keyboardJoysticks": [
    {
      "axisConfig": [
        {},
        {
          "decKey": 81,
          "incKey": 65
        },
        {
          "incKey": 83
        },
        {
          "incKey": 70
        },
        {},
        {
          "decKey": 69,
          "incKey": 68
        }
      ],
      "axisCount": 6,
      "buttonCount": 6,
      "buttonKeys": [
        90,
        88,
        67,
        86,
        87,
        82,
        -1,
        -1,
        -1,
        -1,
        -1,
        -1
      ],
      "povConfig": [
        {
          "key0": 265,
          "key180": 264,
          "key270": 263,
          "key90": 262
        }
      ],
      "povCount": 1
    },
    {
      "axisConfig": [
        {},
        {
          "decKey": 72,
          "incKey": 89
        },
        {
          "incKey": 74
        },
        {
          "incKey": 76
        },
        {},
        {
          "decKey": 75,
          "incKey": 73
        }
      ],
      "axisCount": 6,
      "buttonCount": 6,
      "buttonKeys": [
        66,
        78,
        77,
        44,
        85,
        79,
        -1,
        -1,
        -1,
        -1,
        -1,
        -1,
        -1,
        -1,
        -1
      ],
      "povConfig": [
        {
          "key0": 328,
          "key180": 322,
          "key270": 324,
          "key90": 326
        }
      ],
      "povCount": 1
    },
    {
      "axisCount": 2,
      "buttonCount": 6,
      "buttonKeys": [
        260,
        268,
        266,
        261,
        269,
        267
      ],
      "povCount": 0
    },
    {
      "axisCount": 0,
      "buttonCount": 0,
      "povCount": 0
    }
  ],
  "robotJoysticks": [
    {
      "guid": "78696e70757401000000000000000000",
      "useGamepad": true
    },
    {
      "guid": "Keyboard0"
    }
  ]
}
